.gitignore
CHANGELOG
LICENSE
MANIFEST.in
README.rst
setup.cfg
setup.py
test_requirements.txt
tox.ini
anosql/__init__.py
anosql/core.py
anosql/exceptions.py
anosql/patterns.py
anosql.egg-info/PKG-INFO
anosql.egg-info/SOURCES.txt
anosql.egg-info/dependency_links.txt
anosql.egg-info/top_level.txt
anosql/adapters/__init__.py
anosql/adapters/psycopg2.py
anosql/adapters/sqlite3.py
docs/Makefile
docs/conf.py
docs/defining_queries.rst
docs/extending.rst
docs/getting_started.rst
docs/index.rst
docs/make.bat
docs/upgrading.rst
docs/source/anosql.adapters.psycopg2.rst
docs/source/anosql.adapters.rst
docs/source/anosql.adapters.sqlite3.rst
docs/source/anosql.core.rst
docs/source/anosql.exceptions.rst
docs/source/anosql.patterns.rst
docs/source/anosql.rst
docs/source/modules.rst
tests/__init__.py
tests/conftest.py
tests/test_psycopg2.py
tests/test_simple.py
tests/test_sqlite3.py
tests/blogdb/data/blogs_data.csv
tests/blogdb/data/users_data.csv
tests/blogdb/sql/blogs/blogs.sql
tests/blogdb/sql/blogs/blogs_pg.sql
tests/blogdb/sql/blogs/blogs_sqlite.sql
tests/blogdb/sql/users/users.sql