Metadata-Version: 1.2
Name: anosql
Version: 1.0.2
Summary: Easy SQL in Python
Home-page: https://github.com/honza/anosql
Author: Honza Pokorny
Author-email: me@honza.ca
Maintainer: Honza Pokorny
Maintainer-email: me@honza.ca
License: UNKNOWN
Platform: UNKNOWN
